mlagents_video_streamer/__init__.py
mlagents_video_streamer/setupVirtualDisplay.py
mlagents_video_streamer/streamer.py
mlagents_video_streamer/videoStreamer.py
mlagents_video_streamer-2.0.dist-info/LICENSE
mlagents_video_streamer-2.0.dist-info/METADATA
mlagents_video_streamer-2.0.dist-info/WHEEL
mlagents_video_streamer-2.0.dist-info/top_level.txt
mlagents_video_streamer-2.0.dist-info/RECORD
