Metadata-Version: 2.1
Name: mlagents-video-streamer
Version: 2.0
Summary: Live stream Unity's ML-Agents training process from Google Colab to Twitch/YouTube server.
Home-page: https://github.com/dhyeythumar/mlagents-video-streamer
Author: Dhyey Thumar
Author-email: dhyeythumar@gmail.com
License: UNKNOWN
Keywords: ML-Agents,Video Streamer,Unity Engine,Google Colab
Platform: UNKNOWN
Classifier: Intended Audience :: Science/Research
Classifier: Topic :: Scientific/Engineering :: Artificial Intelligence
Classifier: License :: OSI Approved :: MIT License
Classifier: Operating System :: POSIX :: Linux
Classifier: Programming Language :: Python :: 3
Classifier: Topic :: Software Development :: Libraries
